refcursed/__init__.py
refcursed-0.1.1.dist-info/LICENSE
refcursed-0.1.1.dist-info/METADATA
refcursed-0.1.1.dist-info/WHEEL
refcursed-0.1.1.dist-info/top_level.txt
refcursed-0.1.1.dist-info/RECORD
