Metadata-Version: 2.1
Name: refcursed
Version: 0.1.1
Summary: A library for cursed refcount-based utilities
Home-page: https://github.com/Kylebrown9/refcursed
Author: Kyle Brown
License: MIT
Platform: UNKNOWN
Classifier: License :: OSI Approved :: MIT License
Classifier: Programming Language :: Python
Classifier: Programming Language :: Python :: 3
License-File: LICENSE
